deepseek_coder/__init__.py
deepseek_coder/deepseek_coder.py
deepseek_coder/deepseek_coder.sh
deepseek_coder-0.1.0.dist-info/LICENSE
deepseek_coder-0.1.0.dist-info/METADATA
deepseek_coder-0.1.0.dist-info/WHEEL
deepseek_coder-0.1.0.dist-info/RECORD
